{"schemaVersion":9,"sport":"mlb","processed":["2026-06-24|191642815","2026-06-24|191642814","2026-06-24|191642813","2026-06-24|191642811","2026-06-24|191642809"],"approaches":{"mid|balanced|broad":{"nPortfolios":349,"nEntries":7072,"nCash":1579,"net":-6325.521335861388,"wNet":-8112.521335861388,"fee":17648.75,"sumCumOwn":45380.03563017725,"cumOwnN":349,"sumOverlap":659.5849848625836,"overlapN":349,"sum100":20},"mid|contrarian|broad":{"nPortfolios":158,"nEntries":3160,"nCash":595,"net":-2812.564705882353,"wNet":-2845.814705882353,"fee":5958.75,"sumCumOwn":17472.903485789408,"cumOwnN":158,"sumOverlap":262.3825887103022,"overlapN":158,"sum100":4},"mid|chalky|broad":{"nPortfolios":127,"nEntries":2391,"nCash":706,"net":-1601.8342906030337,"wNet":-1810.0842906030337,"fee":5826.75,"sumCumOwn":18966.540870195535,"cumOwnN":127,"sumOverlap":405.20443969183464,"overlapN":127,"sum100":27},"small|chalky|broad":{"nPortfolios":95,"nEntries":374,"nCash":126,"net":52106.583333333336,"wNet":-69.08333333333337,"fee":1943,"sumCumOwn":14457.253222222222,"cumOwnN":95,"sumOverlap":257.86984126984134,"overlapN":95,"sum100":105},"small|chalky|single":{"nPortfolios":142,"nEntries":142,"nCash":58,"net":148.16666666666663,"wNet":-256.5,"fee":1155,"sumCumOwn":22880.450000000015,"cumOwnN":142,"sumOverlap":0,"overlapN":0,"sum100":1420},"small|balanced|broad":{"nPortfolios":136,"nEntries":579,"nCash":170,"net":-1053.75,"wNet":-1573.75,"fee":4140.25,"sumCumOwn":17666.86774206348,"cumOwnN":136,"sumOverlap":298.94365079365076,"overlapN":136,"sum100":114},"small|chalky|narrow":{"nPortfolios":24,"nEntries":69,"nCash":19,"net":-53,"wNet":-134,"fee":476,"sumCumOwn":3803.125833333333,"cumOwnN":24,"sumOverlap":195.33333333333331,"overlapN":24,"sum100":185},"small|balanced|narrow":{"nPortfolios":10,"nEntries":30,"nCash":10,"net":-86.5,"wNet":-147.5,"fee":371.5,"sumCumOwn":1323.1389999999997,"cumOwnN":10,"sumOverlap":80.56666666666668,"overlapN":10,"sum100":74},"small|balanced|single":{"nPortfolios":86,"nEntries":86,"nCash":27,"net":125.5,"wNet":-132.5,"fee":622.5,"sumCumOwn":11251.360000000002,"cumOwnN":86,"sumOverlap":0,"overlapN":0,"sum100":860},"small|contrarian|broad":{"nPortfolios":73,"nEntries":320,"nCash":48,"net":-1238.4166666666665,"wNet":-1238.4166666666665,"fee":1746.25,"sumCumOwn":7917.013333333335,"cumOwnN":73,"sumOverlap":164.57936507936515,"overlapN":73,"sum100":59},"mid|chalky|narrow":{"nPortfolios":10,"nEntries":198,"nCash":67,"net":-18.861111111111114,"wNet":-18.861111111111114,"fee":119,"sumCumOwn":1578.9474395604395,"cumOwnN":10,"sumOverlap":73.56707870732639,"overlapN":10,"sum100":47},"mid|balanced|narrow":{"nPortfolios":7,"nEntries":130,"nCash":43,"net":-24,"wNet":-24,"fee":70,"sumCumOwn":907.8575000000001,"cumOwnN":7,"sumOverlap":57.294736842105266,"overlapN":7,"sum100":37},"small|contrarian|single":{"nPortfolios":72,"nEntries":72,"nCash":14,"net":-461.5,"wNet":-461.5,"fee":648.5,"sumCumOwn":7494.3499999999985,"cumOwnN":72,"sumOverlap":0,"overlapN":0,"sum100":720},"small|contrarian|narrow":{"nPortfolios":5,"nEntries":18,"nCash":0,"net":-165.5,"wNet":-165.5,"fee":165.5,"sumCumOwn":551.86,"cumOwnN":5,"sumOverlap":47,"overlapN":5,"sum100":47},"mid|contrarian|narrow":{"nPortfolios":3,"nEntries":52,"nCash":1,"net":-101.5,"wNet":-101.5,"fee":103,"sumCumOwn":322.73350000000005,"cumOwnN":3,"sumOverlap":21.019138755980862,"overlapN":3,"sum100":8},"max|balanced|broad":{"nPortfolios":164,"nEntries":21308,"nCash":4686,"net":-28419.2611172771,"wNet":-30568.166777654456,"fee":66321.5,"sumCumOwn":20641.457012946044,"cumOwnN":164,"sumOverlap":267.7583933139165,"overlapN":164,"sum100":5},"max|chalky|broad":{"nPortfolios":32,"nEntries":4091,"nCash":1176,"net":-5780.302534221236,"wNet":-5780.302534221236,"fee":15170.5,"sumCumOwn":4594.724913207547,"cumOwnN":32,"sumOverlap":87.49134212031126,"overlapN":32,"sum100":4},"max|contrarian|broad":{"nPortfolios":41,"nEntries":5113,"nCash":836,"net":-21485.521698113207,"wNet":-21485.521698113207,"fee":29436.5,"sumCumOwn":4510.021127965011,"cumOwnN":41,"sumOverlap":69.00697823613682,"overlapN":41,"sum100":1},"mid|unclassified|narrow":{"nPortfolios":1,"nEntries":16,"nCash":0,"net":-8,"wNet":-8,"fee":8,"sumCumOwn":0,"cumOwnN":0,"sumOverlap":0,"overlapN":1,"sum100":0},"small|unclassified|narrow":{"nPortfolios":1,"nEntries":2,"nCash":0,"net":-8,"wNet":-8,"fee":8,"sumCumOwn":0,"cumOwnN":0,"sumOverlap":0,"overlapN":1,"sum100":0}},"coverage":{"team":0,"price":0,"contests":5},"lastScan":"2026-06-25T18:34:42.593Z"}